folktables/__init__.py
folktables/acs.py
folktables/exceptions.py
folktables/folktables.py
folktables/load_acs.py
folktables/utils/__init__.py
folktables/utils/download_utils.py
folktables/utils/files_resources.py
folktables/utils/load_utils.py
tests/__init__.py
tests/test_examples.py
tests/test_pandas.py
tests/test_problem.py
tests/utils/__init__.py
tests/utils/test_download_utils.py
tests/utils/test_files_resource.py
tests/utils/test_load_utils.py
folktables-0.0.12.dist-info/LICENSE.txt
folktables-0.0.12.dist-info/METADATA
folktables-0.0.12.dist-info/WHEEL
folktables-0.0.12.dist-info/top_level.txt
folktables-0.0.12.dist-info/RECORD
